opengauss_sqlalchemy/__init__.py
opengauss_sqlalchemy/asyncpg.py
opengauss_sqlalchemy/base.py
opengauss_sqlalchemy/dc_psycopg2.py
opengauss_sqlalchemy/provision.py
opengauss_sqlalchemy/psycopg2.py
opengauss_sqlalchemy/register_async.py
opengauss_sqlalchemy/requirements.py
opengauss_sqlalchemy/usertype/__init__.py
opengauss_sqlalchemy/usertype/bit.py
opengauss_sqlalchemy/usertype/sparsevec.py
opengauss_sqlalchemy/usertype/vector.py
opengauss_sqlalchemy/utils/__init__.py
opengauss_sqlalchemy/utils/bit.py
opengauss_sqlalchemy/utils/sparsevec.py
opengauss_sqlalchemy/utils/vector.py
opengauss_sqlalchemy-2.4.0.dist-info/LICENSE.md
opengauss_sqlalchemy-2.4.0.dist-info/METADATA
opengauss_sqlalchemy-2.4.0.dist-info/WHEEL
opengauss_sqlalchemy-2.4.0.dist-info/entry_points.txt
opengauss_sqlalchemy-2.4.0.dist-info/top_level.txt
opengauss_sqlalchemy-2.4.0.dist-info/RECORD
